sopel_itcrowd/__init__.py
sopel_itcrowd/plugin.py
sopel_itcrowd-0.1.0.dist-info/COPYING
sopel_itcrowd-0.1.0.dist-info/METADATA
sopel_itcrowd-0.1.0.dist-info/WHEEL
sopel_itcrowd-0.1.0.dist-info/entry_points.txt
sopel_itcrowd-0.1.0.dist-info/top_level.txt
sopel_itcrowd-0.1.0.dist-info/RECORD
